[
  {
    "id": "USR06812",
    "profile": {
      "name": "User78",
      "contact": {
        "email": "user78@example.com",
        "phone": "555-9368"
      }
    },
    "metrics": {
      "score": 1,
      "level": 9
    }
  },
  {
    "id": "USR09843",
    "profile": {
      "name": "User592",
      "contact": {
        "email": "user592@example.com",
        "phone": "555-5409"
      }
    },
    "metrics": {
      "score": 72,
      "level": 7
    }
  },
  {
    "id": "USR03514",
    "profile": {
      "name": "User504",
      "contact": {
        "email": "user504@example.com",
        "phone": "555-5584"
      }
    },
    "metrics": {
      "score": 4,
      "level": 3
    }
  },
  {
    "id": "USR08154",
    "profile": {
      "name": "User890",
      "contact": {
        "email": "user890@example.com",
        "phone": "555-5647"
      }
    },
    "metrics": {
      "score": 88,
      "level": 2
    }
  },
  {
    "id": "USR01325",
    "profile": {
      "name": "User259",
      "contact": {
        "email": "user259@example.com",
        "phone": "555-3683"
      }
    },
    "metrics": {
      "score": 91,
      "level": 1
    }
  },
  {
    "id": "USR06782",
    "profile": {
      "name": "User219",
      "contact": {
        "email": "user219@example.com",
        "phone": "555-4080"
      }
    },
    "metrics": {
      "score": 27,
      "level": 3
    }
  },
  {
    "id": "USR00252",
    "profile": {
      "name": "User897",
      "contact": {
        "email": "user897@example.com",
        "phone": "555-9292"
      }
    },
    "metrics": {
      "score": 51,
      "level": 10
    }
  },
  {
    "id": "USR09791",
    "profile": {
      "name": "User630",
      "contact": {
        "email": "user630@example.com",
        "phone": "555-1000"
      }
    },
    "metrics": {
      "score": 19,
      "level": 7
    }
  },
  {
    "id": "USR07363",
    "profile": {
      "name": "User829",
      "contact": {
        "email": "user829@example.com",
        "phone": "555-1583"
      }
    },
    "metrics": {
      "score": 1,
      "level": 5
    }
  },
  {
    "id": "USR05897",
    "profile": {
      "name": "User725",
      "contact": {
        "email": "user725@example.com",
        "phone": "555-1011"
      }
    },
    "metrics": {
      "score": 24,
      "level": 4
    }
  },
  {
    "id": "USR03273",
    "profile": {
      "name": "User679",
      "contact": {
        "email": "user679@example.com",
        "phone": "555-1229"
      }
    },
    "metrics": {
      "score": 21,
      "level": 8
    }
  }
]