[
  {
    "id": "USR02010",
    "profile": {
      "name": "User251",
      "contact": {
        "email": "user251@example.com",
        "phone": "555-3029"
      }
    },
    "metrics": {
      "score": 67,
      "level": 5
    }
  },
  {
    "id": "USR07122",
    "profile": {
      "name": "User869",
      "contact": {
        "email": "user869@example.com",
        "phone": "555-3807"
      }
    },
    "metrics": {
      "score": 9,
      "level": 5
    }
  },
  {
    "id": "USR05773",
    "profile": {
      "name": "User868",
      "contact": {
        "email": "user868@example.com",
        "phone": "555-0753"
      }
    },
    "metrics": {
      "score": 89,
      "level": 3
    }
  },
  {
    "id": "USR07557",
    "profile": {
      "name": "User764",
      "contact": {
        "email": "user764@example.com",
        "phone": "555-9263"
      }
    },
    "metrics": {
      "score": 67,
      "level": 2
    }
  },
  {
    "id": "USR07969",
    "profile": {
      "name": "User591",
      "contact": {
        "email": "user591@example.com",
        "phone": "555-6127"
      }
    },
    "metrics": {
      "score": 16,
      "level": 3
    }
  },
  {
    "id": "USR06106",
    "profile": {
      "name": "User493",
      "contact": {
        "email": "user493@example.com",
        "phone": "555-8002"
      }
    },
    "metrics": {
      "score": 85,
      "level": 10
    }
  },
  {
    "id": "USR01709",
    "profile": {
      "name": "User220",
      "contact": {
        "email": "user220@example.com",
        "phone": "555-3256"
      }
    },
    "metrics": {
      "score": 30,
      "level": 2
    }
  },
  {
    "id": "USR07667",
    "profile": {
      "name": "User7",
      "contact": {
        "email": "user7@example.com",
        "phone": "555-8099"
      }
    },
    "metrics": {
      "score": 52,
      "level": 3
    }
  }
]